changetools/__init__.py
changetools/evaluator.py
changetools/py.typed
changetools-0.1.0.dist-info/LICENSE
changetools-0.1.0.dist-info/METADATA
changetools-0.1.0.dist-info/WHEEL
changetools-0.1.0.dist-info/top_level.txt
changetools-0.1.0.dist-info/RECORD
