Metadata-Version: 2.1
Name: changetools
Version: 0.1.0
Summary: Change evaluation functions and decorators
License: MIT
Project-URL: Repository, https://github.com/whardier/changetools-python
Classifier: Development Status :: 1 - Planning
Classifier: Intended Audience :: Developers
Classifier: Intended Audience :: Information Technology
Classifier: License :: OSI Approved :: MIT License
Classifier: Programming Language :: Python :: 3 :: Only
Classifier: Programming Language :: Python :: 3.10
Classifier: Programming Language :: Python :: 3.11
Classifier: Programming Language :: Python :: 3.7
Classifier: Programming Language :: Python :: 3.8
Classifier: Programming Language :: Python :: 3.9
Classifier: Programming Language :: Python :: 3
Classifier: Programming Language :: Python
Classifier: Topic :: Software Development :: Code Generators
Classifier: Topic :: Software Development :: Libraries :: Python Modules
Classifier: Topic :: Software Development :: Libraries
Classifier: Topic :: Text Processing :: Filters
Classifier: Topic :: Text Processing :: General
Classifier: Topic :: Text Processing
Requires-Python: <4.0,>=3.7
License-File: LICENSE
Provides-Extra: dev
Requires-Dist: black (~=22.10) ; extra == 'dev'
Requires-Dist: build (~=0.9) ; extra == 'dev'
Requires-Dist: flake8-awesome (~=1.3) ; extra == 'dev'
Requires-Dist: mypy (~=0.991) ; extra == 'dev'
Requires-Dist: pytest (~=7.2) ; extra == 'dev'
Requires-Dist: tox (~=3.27) ; extra == 'dev'
Requires-Dist: twine (~=4.0) ; extra == 'dev'
